src/__init__.py
src/dashboard.py
src/settings.py
src/utils.py
bruise_fusion-0.2.1.dist-info/METADATA
bruise_fusion-0.2.1.dist-info/WHEEL
bruise_fusion-0.2.1.dist-info/entry_points.txt
bruise_fusion-0.2.1.dist-info/top_level.txt
bruise_fusion-0.2.1.dist-info/RECORD
