Metadata-Version: 2.4
Name: bruise-fusion
Version: 0.2.1
Summary: Spatial-frequency fusion of white-light and ALS images for bruise analysis
Home-page: https://github.com/artinmajdi/bruise_fusion
Author: Artin Majdi
Author-email: Artin Majdi <mmajdi@gmu.edu>
License: MIT
Project-URL: Homepage, https://github.com/artinmajdi/RAP
Project-URL: Repository, https://github.com/artinmajdi/RAP.git
Project-URL: Issues, https://github.com/artinmajdi/RAP/issues
Classifier: Development Status :: 4 - Beta
Classifier: Intended Audience :: Science/Research
Classifier: License :: OSI Approved :: MIT License
Classifier: Operating System :: OS Independent
Classifier: Natural Language :: English
Classifier: Programming Language :: Python :: 3
Classifier: Programming Language :: Python :: 3 :: Only
Classifier: Programming Language :: Python :: 3.10
Classifier: Programming Language :: Python :: 3.11
Classifier: Programming Language :: Python :: 3.12
Classifier: Programming Language :: Python :: Implementation :: CPython
Classifier: Topic :: Scientific/Engineering :: Image Processing
Classifier: Topic :: Scientific/Engineering :: Medical Science Apps.
Requires-Python: >=3.10
Requires-Dist: opencv-python>=4.12.0
Requires-Dist: numpy>=2.2.0
Requires-Dist: matplotlib>=3.10.0
Requires-Dist: streamlit>=1.28.0
Requires-Dist: Pillow>=9.0.0
Requires-Dist: pandas>=2.3.0
Requires-Dist: seaborn>=0.13.0
Requires-Dist: watchdog>=6.0.0
Requires-Dist: pywavelets>=1.8.0
Requires-Dist: scikit-image>=0.25.2
Requires-Dist: rich>=14.1.0
Requires-Dist: rawpy>=0.21.0
Requires-Dist: imageio>=2.37.0
Requires-Dist: dotenv>=0.9.9
Dynamic: author
Dynamic: home-page
Dynamic: requires-python
